biketrauma/__init__.py
biketrauma/io/Load_db.py
biketrauma/io/__init__.py
biketrauma/preprocess/__init2__.py
biketrauma/preprocess/format_date.py
biketrauma/preprocess/get_accident.py
biketrauma/vis/__init__.py
biketrauma/vis/plot_location.py
biketrauma-0.0.1.dist-info/METADATA
biketrauma-0.0.1.dist-info/WHEEL
biketrauma-0.0.1.dist-info/top_level.txt
biketrauma-0.0.1.dist-info/RECORD
