Metadata-Version: 2.1
Name: biketrauma
Version: 0.0.1
Summary: Visualization of a bicycle accident db
Home-page: http://github.com/xxxxxxxxxxx.git
Author: xxxxxxxxxxx
Author-email: xxxxxxxxxx@xxxxxxxxxxxxx.xxx
License: MIT
Platform: UNKNOWN
